forsitepy/__init__.py
forsitepy/__version__.py
forsitepy/commonstuff.py
forsitepy/validation.py
forsitepy-1.1.8.dist-info/LICENSE
forsitepy-1.1.8.dist-info/METADATA
forsitepy-1.1.8.dist-info/WHEEL
forsitepy-1.1.8.dist-info/top_level.txt
forsitepy-1.1.8.dist-info/RECORD
