Metadata-Version: 2.2
Name: forsitepy
Version: 1.1.8
Summary: Common libraries used within forsite
Author-email: Pawel Migdal <pmigdal@forsite.ca>
Project-URL: Homepage, https://github.com/ForsiteConsultants/forsitepy
Project-URL: Issues, https://github.com/ForsiteConsultants/forsitepy/issues
Classifier: Programming Language :: Python :: 3
Classifier: License :: OSI Approved :: MIT License
Classifier: Operating System :: OS Independent
Requires-Python: >=3.8
License-File: LICENSE
Requires-Dist: pandas
Requires-Dist: numpy
Requires-Dist: py-machineid
Requires-Dist: requests
